pretix_visma_pay/__init__.py
pretix_visma_pay/payment.py
pretix_visma_pay/signals.py
pretix_visma_pay/urls.py
pretix_visma_pay/utils.py
pretix_visma_pay/views.py
pretix_visma_pay/visma_pay.py
pretix_visma_pay/locale/de/LC_MESSAGES/django.mo
pretix_visma_pay/locale/de/LC_MESSAGES/django.po
pretix_visma_pay/locale/de_Informal/.gitkeep
pretix_visma_pay/locale/de_Informal/LC_MESSAGES/django.mo
pretix_visma_pay/locale/de_Informal/LC_MESSAGES/django.po
pretix_visma_pay/locale/en/LC_MESSAGES/django.mo
pretix_visma_pay/locale/en/LC_MESSAGES/django.po
pretix_visma_pay/locale/fi/LC_MESSAGES/django.mo
pretix_visma_pay/locale/fi/LC_MESSAGES/django.po
pretix_visma_pay/static/pretix_visma_pay/.gitkeep
pretix_visma_pay/static/pretix_visma_pay/payment_methods_banner.png
pretix_visma_pay/templates/pretix_visma_pay/.gitkeep
pretix_visma_pay/templates/pretix_visma_pay/payment_form.html
pretix_visma_pay_alt-0.4.2.dist-info/LICENSE
pretix_visma_pay_alt-0.4.2.dist-info/METADATA
pretix_visma_pay_alt-0.4.2.dist-info/WHEEL
pretix_visma_pay_alt-0.4.2.dist-info/entry_points.txt
pretix_visma_pay_alt-0.4.2.dist-info/top_level.txt
pretix_visma_pay_alt-0.4.2.dist-info/RECORD
